__init__.py
config.py
main.py
models.py
utils.py
pepperbot_gpt_example-0.0.1.dist-info/METADATA
pepperbot_gpt_example-0.0.1.dist-info/WHEEL
pepperbot_gpt_example-0.0.1.dist-info/top_level.txt
pepperbot_gpt_example-0.0.1.dist-info/RECORD
